setup.py
genius_cli/__init__.py
genius_cli/blocks.py
genius_cli/client.py
genius_cli/main.py
genius_cli/utils.py
zmei.egg-info/PKG-INFO
zmei.egg-info/SOURCES.txt
zmei.egg-info/dependency_links.txt
zmei.egg-info/entry_points.txt
zmei.egg-info/requires.txt
zmei.egg-info/top_level.txt